<annotation>
	<folder>Training_samples</folder>
	<filename>outside1590.jpg</filename>
	<path>D:\self_driving_car\Tutorial\Training_samples\outside1590.jpg</path>
	<source>
		<database>Unknown</database>
	</source>
	<size>
		<width>640</width>
		<height>480</height>
		<depth>3</depth>
	</size>
	<segmented>0</segmented>
	<object>
		<name>red</name>
		<pose>Unspecified</pose>
		<truncated>0</truncated>
		<difficult>0</difficult>
		<bndbox>
			<xmin>280</xmin>
			<ymin>101</ymin>
			<xmax>314</xmax>
			<ymax>181</ymax>
		</bndbox>
	</object>
</annotation>
